setup.py
alfred_npm_helper/__init__.py
alfred_npm_helper/data.py
alfred_npm_helper/entry.py
alfred_npm_helper.egg-info/PKG-INFO
alfred_npm_helper.egg-info/SOURCES.txt
alfred_npm_helper.egg-info/dependency_links.txt
alfred_npm_helper.egg-info/not-zip-safe
alfred_npm_helper.egg-info/requires.txt
alfred_npm_helper.egg-info/top_level.txt
alfred_npm_helper/spiders/__init__.py
alfred_npm_helper/spiders/spider_list.py
alfred_npm_helper/spiders/spider_page.py